softdtree/__init__.py
softdtree/_softdtree.abi3.so
softdtree/_softdtree.pyi
softdtree/py.typed
softdtree-0.1.0.dist-info/METADATA
softdtree-0.1.0.dist-info/WHEEL
softdtree-0.1.0.dist-info/licenses/LICENSE.txt
softdtree-0.1.0.dist-info/RECORD
