Metadata-Version: 2.4
Name: softdtree
Version: 0.1.0
Summary: A Python library that implements classifier and regressor with Soft Decision Tree.
Author-Email: Atsushi Tatsuma <yoshoku@outlook.com>
License-Expression: BSD-3-Clause
Project-URL: Homepage, https://github.com/yoshoku/softdtree
Project-URL: Repository, https://github.com/yoshoku/softdtree
Project-URL: Issues, https://github.com/yoshoku/softdtree/issues
Requires-Python: >=3.10
Requires-Dist: scikit-learn>=1.6.1
Requires-Dist: numpy>=1.21.0
